panoramax_gopro_downloader/__init__.py
panoramax_gopro_downloader/app.py
panoramax_gopro_downloader-0.1.0.dist-info/licenses/COPYING
panoramax_gopro_downloader-0.1.0.dist-info/WHEEL
panoramax_gopro_downloader-0.1.0.dist-info/entry_points.txt
panoramax_gopro_downloader-0.1.0.dist-info/METADATA
panoramax_gopro_downloader-0.1.0.dist-info/RECORD
