Metadata-Version: 2.4
Name: panoramax-gopro-downloader
Version: 0.1.0
Summary: Copy JPG files from a GoPro SD card to split them into sequences by recording
Keywords: panoramax,gopro,file copier
Author: Bastian Greshake Tzovaras
Author-email: Bastian Greshake Tzovaras <bgreshake@proton.me>
License-Expression: AGPL-3.0-or-later
License-File: COPYING
Requires-Dist: click>=8.3.1
Requires-Dist: rich>=14.2.0
Requires-Python: >=3.14
Project-URL: Funding, https://ko-fi.com/gedankenstuecke
Project-URL: Homepage, https://codeberg.org/gedankenstuecke/panoramax-gopro-downloader
Project-URL: Issues, https://codeberg.org/gedankenstuecke/panoramax-gopro-downloader/issues
Project-URL: Repository, https://codeberg.org/gedankenstuecke/panoramax-gopro-downloader.git
